ravel/__init__.py
ravel/api.py
ravel/batch.py
ravel/constants.py
ravel/dumper.py
ravel/entity.py
ravel/exceptions.py
ravel/logging.py
ravel/resource.py
ravel/schema.py
ravel/usage.py
ravel/app/__init__.py
ravel/app/exceptions.py
ravel/app/base/__init__.py
ravel/app/base/action.py
ravel/app/base/action_decorator.py
ravel/app/base/application.py
ravel/app/base/argument_loader.py
ravel/app/base/resource_binder.py
ravel/app/middleware/__init__.py
ravel/app/middleware/manage_session.py
ravel/app/middleware/middleware.py
ravel/app/middleware/guard_middleware/__init__.py
ravel/app/middleware/guard_middleware/argument.py
ravel/app/middleware/guard_middleware/evaluate_guards.py
ravel/app/middleware/guard_middleware/guard.py
ravel/app/template/__init__.py
ravel/app/template/jinja_renderer.py
ravel/app/template/renderer.py
ravel/apps/__init__.py
ravel/apps/async_server.py
ravel/apps/cli.py
ravel/apps/repl.py
ravel/apps/web/__init__.py
ravel/apps/web/abstract_http_server.py
ravel/apps/web/abstract_wsgi_service.py
ravel/apps/web/http_server.py
ravel/apps/web/websocket_server.py
ravel/components/__init__.py
ravel/components/recursive_list.py
ravel/components/session.py
ravel/components/user.py
ravel/ext/__init__.py
ravel/ext/celery/__init__.py
ravel/ext/celery/celery_service.py
ravel/ext/celery/celery_task.py
ravel/ext/celery/middleware.py
ravel/ext/falcon/__init__.py
ravel/ext/falcon/constants.py
ravel/ext/falcon/exceptions.py
ravel/ext/falcon/media.py
ravel/ext/falcon/resource.py
ravel/ext/falcon/service.py
ravel/ext/falcon/middleware/__init__.py
ravel/ext/falcon/middleware/manage_csrf_token.py
ravel/ext/falcon/middleware/render_template.py
ravel/ext/falcon/middleware/set_http_cors_response_headers.py
ravel/ext/gaming/__init__.py
ravel/ext/gaming/pygame/__init__.py
ravel/ext/gaming/pygame/pygame_game.py
ravel/ext/graphql/__init__.py
ravel/ext/graphql/graphql_arguments.py
ravel/ext/graphql/graphql_interpreter.py
ravel/ext/graphql/graphql_query.py
ravel/ext/grpc/__init__.py
ravel-3.0.1.dist-info/LICENSE
ravel-3.0.1.dist-info/METADATA
ravel-3.0.1.dist-info/WHEEL
ravel-3.0.1.dist-info/top_level.txt
ravel-3.0.1.dist-info/RECORD
